README.rst
setup.py
keepaneyeon/__init__.py
keepaneyeon/cli.py
keepaneyeon/config.py
keepaneyeon/fortytwomatters.py
keepaneyeon/http.py
keepaneyeon/s3.py
keepaneyeon/target.py
keepaneyeon/versioned.py
keepaneyeon.egg-info/PKG-INFO
keepaneyeon.egg-info/SOURCES.txt
keepaneyeon.egg-info/dependency_links.txt
keepaneyeon.egg-info/entry_points.txt
keepaneyeon.egg-info/requires.txt
keepaneyeon.egg-info/top_level.txt