Metadata-Version: 1.0
Name: keepaneyeon
Version: 0.1.0
Summary: Monitor URLs for changes
Home-page: https://github.com/mmcloughlin/keepaneyeon
Author: Michael McLoughlin
Author-email: mmcloughlin@gmail.com
License: MIT
Platform: UNKNOWN
